{
  "id": "4336321",
  "info_hash": "8eb96d0d4ee71be3cf908ff8d801a1d4a4a91b5e",
  "name": "Greys.Anatomy.S11.1080p.WEBRip.x265-RARBG",
  "folder": "Greys.Anatomy.S11.1080p.WEBRip.x265-RARBG",
  "filename": "Greys.Anatomy.S11.1080p.WEBRip.x265-RARBG",
  "original_filename": "Greys.Anatomy.S11.1080p.WEBRip.x265-RARBG",
  "size": 0,
  "bytes": 17940427968,
  "magnet": null,
  "files": {
    "Greys.Anatomy.S11E01.1080p.WEBRip.x265-RARBG.mp4": {
      "torrent_id": "4336321",
      "id": "8",
      "name": "Greys.Anatomy.S11E01.1080p.WEBRip.x265-RARBG.mp4",
      "size": 719938342,
      "is_rar": false,
      "path": "Greys.Anatomy.S11.1080p.WEBRip.x265-RARBG/Greys.Anatomy.S11E01.1080p.WEBRip.x265-RARBG.mp4",
      "link": "torbox://4336321/8",
      "account_id": "",
      "generated": "0001-01-01T00:00:00Z",
      "deleted": false
    },
    "Greys.Anatomy.S11E02.1080p.WEBRip.x265-RARBG.mp4": {
      "torrent_id": "4336321",
      "id": "22",
      "name": "Greys.Anatomy.S11E02.1080p.WEBRip.x265-RARBG.mp4",
      "size": 719838072,
      "is_rar": false,
      "path": "Greys.Anatomy.S11.1080p.WEBRip.x265-RARBG/Greys.Anatomy.S11E02.1080p.WEBRip.x265-RARBG.mp4",
      "link": "torbox://4336321/22",
      "account_id": "",
      "generated": "0001-01-01T00:00:00Z",
      "deleted": false
    },
    "Greys.Anatomy.S11E03.1080p.WEBRip.x265-RARBG.mp4": {
      "torrent_id": "4336321",
      "id": "9",
      "name": "Greys.Anatomy.S11E03.1080p.WEBRip.x265-RARBG.mp4",
      "size": 720153896,
      "is_rar": false,
      "path": "Greys.Anatomy.S11.1080p.WEBRip.x265-RARBG/Greys.Anatomy.S11E03.1080p.WEBRip.x265-RARBG.mp4",
      "link": "torbox://4336321/9",
      "account_id": "",
      "generated": "0001-01-01T00:00:00Z",
      "deleted": false
    },
    "Greys.Anatomy.S11E04.1080p.WEBRip.x265-RARBG.mp4": {
      "torrent_id": "4336321",
      "id": "20",
      "name": "Greys.Anatomy.S11E04.1080p.WEBRip.x265-RARBG.mp4",
      "size": 720270401,
      "is_rar": false,
      "path": "Greys.Anatomy.S11.1080p.WEBRip.x265-RARBG/Greys.Anatomy.S11E04.1080p.WEBRip.x265-RARBG.mp4",
      "link": "torbox://4336321/20",
      "account_id": "",
      "generated": "0001-01-01T00:00:00Z",
      "deleted": false
    },
    "Greys.Anatomy.S11E05.1080p.WEBRip.x265-RARBG.mp4": {
      "torrent_id": "4336321",
      "id": "10",
      "name": "Greys.Anatomy.S11E05.1080p.WEBRip.x265-RARBG.mp4",
      "size": 719427866,
      "is_rar": false,
      "path": "Greys.Anatomy.S11.1080p.WEBRip.x265-RARBG/Greys.Anatomy.S11E05.1080p.WEBRip.x265-RARBG.mp4",
      "link": "torbox://4336321/10",
      "account_id": "",
      "generated": "0001-01-01T00:00:00Z",
      "deleted": false
    },
    "Greys.Anatomy.S11E06.1080p.WEBRip.x265-RARBG.mp4": {
      "torrent_id": "4336321",
      "id": "21",
      "name": "Greys.Anatomy.S11E06.1080p.WEBRip.x265-RARBG.mp4",
      "size": 720528312,
      "is_rar": false,
      "path": "Greys.Anatomy.S11.1080p.WEBRip.x265-RARBG/Greys.Anatomy.S11E06.1080p.WEBRip.x265-RARBG.mp4",
      "link": "torbox://4336321/21",
      "account_id": "",
      "generated": "0001-01-01T00:00:00Z",
      "deleted": false
    },
    "Greys.Anatomy.S11E07.1080p.WEBRip.x265-RARBG.mp4": {
      "torrent_id": "4336321",
      "id": "12",
      "name": "Greys.Anatomy.S11E07.1080p.WEBRip.x265-RARBG.mp4",
      "size": 719904856,
      "is_rar": false,
      "path": "Greys.Anatomy.S11.1080p.WEBRip.x265-RARBG/Greys.Anatomy.S11E07.1080p.WEBRip.x265-RARBG.mp4",
      "link": "torbox://4336321/12",
      "account_id": "",
      "generated": "0001-01-01T00:00:00Z",
      "deleted": false
    },
    "Greys.Anatomy.S11E08.1080p.WEBRip.x265-RARBG.mp4": {
      "torrent_id": "4336321",
      "id": "19",
      "name": "Greys.Anatomy.S11E08.1080p.WEBRip.x265-RARBG.mp4",
      "size": 720019518,
      "is_rar": false,
      "path": "Greys.Anatomy.S11.1080p.WEBRip.x265-RARBG/Greys.Anatomy.S11E08.1080p.WEBRip.x265-RARBG.mp4",
      "link": "torbox://4336321/19",
      "account_id": "",
      "generated": "0001-01-01T00:00:00Z",
      "deleted": false
    },
    "Greys.Anatomy.S11E09.1080p.WEBRip.x265-RARBG.mp4": {
      "torrent_id": "4336321",
      "id": "7",
      "name": "Greys.Anatomy.S11E09.1080p.WEBRip.x265-RARBG.mp4",
      "size": 719805494,
      "is_rar": false,
      "path": "Greys.Anatomy.S11.1080p.WEBRip.x265-RARBG/Greys.Anatomy.S11E09.1080p.WEBRip.x265-RARBG.mp4",
      "link": "torbox://4336321/7",
      "account_id": "",
      "generated": "0001-01-01T00:00:00Z",
      "deleted": false
    },
    "Greys.Anatomy.S11E10.1080p.WEBRip.x265-RARBG.mp4": {
      "torrent_id": "4336321",
      "id": "16",
      "name": "Greys.Anatomy.S11E10.1080p.WEBRip.x265-RARBG.mp4",
      "size": 719975649,
      "is_rar": false,
      "path": "Greys.Anatomy.S11.1080p.WEBRip.x265-RARBG/Greys.Anatomy.S11E10.1080p.WEBRip.x265-RARBG.mp4",
      "link": "torbox://4336321/16",
      "account_id": "",
      "generated": "0001-01-01T00:00:00Z",
      "deleted": false
    },
    "Greys.Anatomy.S11E11.1080p.WEBRip.x265-RARBG.mp4": {
      "torrent_id": "4336321",
      "id": "6",
      "name": "Greys.Anatomy.S11E11.1080p.WEBRip.x265-RARBG.mp4",
      "size": 719353203,
      "is_rar": false,
      "path": "Greys.Anatomy.S11.1080p.WEBRip.x265-RARBG/Greys.Anatomy.S11E11.1080p.WEBRip.x265-RARBG.mp4",
      "link": "torbox://4336321/6",
      "account_id": "",
      "generated": "0001-01-01T00:00:00Z",
      "deleted": false
    },
    "Greys.Anatomy.S11E12.1080p.WEBRip.x265-RARBG.mp4": {
      "torrent_id": "4336321",
      "id": "15",
      "name": "Greys.Anatomy.S11E12.1080p.WEBRip.x265-RARBG.mp4",
      "size": 720164033,
      "is_rar": false,
      "path": "Greys.Anatomy.S11.1080p.WEBRip.x265-RARBG/Greys.Anatomy.S11E12.1080p.WEBRip.x265-RARBG.mp4",
      "link": "torbox://4336321/15",
      "account_id": "",
      "generated": "0001-01-01T00:00:00Z",
      "deleted": false
    },
    "Greys.Anatomy.S11E13.1080p.WEBRip.x265-RARBG.mp4": {
      "torrent_id": "4336321",
      "id": "5",
      "name": "Greys.Anatomy.S11E13.1080p.WEBRip.x265-RARBG.mp4",
      "size": 720088475,
      "is_rar": false,
      "path": "Greys.Anatomy.S11.1080p.WEBRip.x265-RARBG/Greys.Anatomy.S11E13.1080p.WEBRip.x265-RARBG.mp4",
      "link": "torbox://4336321/5",
      "account_id": "",
      "generated": "0001-01-01T00:00:00Z",
      "deleted": false
    },
    "Greys.Anatomy.S11E14.1080p.WEBRip.x265-RARBG.mp4": {
      "torrent_id": "4336321",
      "id": "18",
      "name": "Greys.Anatomy.S11E14.1080p.WEBRip.x265-RARBG.mp4",
      "size": 720135889,
      "is_rar": false,
      "path": "Greys.Anatomy.S11.1080p.WEBRip.x265-RARBG/Greys.Anatomy.S11E14.1080p.WEBRip.x265-RARBG.mp4",
      "link": "torbox://4336321/18",
      "account_id": "",
      "generated": "0001-01-01T00:00:00Z",
      "deleted": false
    },
    "Greys.Anatomy.S11E15.1080p.WEBRip.x265-RARBG.mp4": {
      "torrent_id": "4336321",
      "id": "4",
      "name": "Greys.Anatomy.S11E15.1080p.WEBRip.x265-RARBG.mp4",
      "size": 720162424,
      "is_rar": false,
      "path": "Greys.Anatomy.S11.1080p.WEBRip.x265-RARBG/Greys.Anatomy.S11E15.1080p.WEBRip.x265-RARBG.mp4",
      "link": "torbox://4336321/4",
      "account_id": "",
      "generated": "0001-01-01T00:00:00Z",
      "deleted": false
    },
    "Greys.Anatomy.S11E16.1080p.WEBRip.x265-RARBG.mp4": {
      "torrent_id": "4336321",
      "id": "17",
      "name": "Greys.Anatomy.S11E16.1080p.WEBRip.x265-RARBG.mp4",
      "size": 720059987,
      "is_rar": false,
      "path": "Greys.Anatomy.S11.1080p.WEBRip.x265-RARBG/Greys.Anatomy.S11E16.1080p.WEBRip.x265-RARBG.mp4",
      "link": "torbox://4336321/17",
      "account_id": "",
      "generated": "0001-01-01T00:00:00Z",
      "deleted": false
    },
    "Greys.Anatomy.S11E17.1080p.WEBRip.x265-RARBG.mp4": {
      "torrent_id": "4336321",
      "id": "3",
      "name": "Greys.Anatomy.S11E17.1080p.WEBRip.x265-RARBG.mp4",
      "size": 719828999,
      "is_rar": false,
      "path": "Greys.Anatomy.S11.1080p.WEBRip.x265-RARBG/Greys.Anatomy.S11E17.1080p.WEBRip.x265-RARBG.mp4",
      "link": "torbox://4336321/3",
      "account_id": "",
      "generated": "0001-01-01T00:00:00Z",
      "deleted": false
    },
    "Greys.Anatomy.S11E18.1080p.WEBRip.x265-RARBG.mp4": {
      "torrent_id": "4336321",
      "id": "13",
      "name": "Greys.Anatomy.S11E18.1080p.WEBRip.x265-RARBG.mp4",
      "size": 719793640,
      "is_rar": false,
      "path": "Greys.Anatomy.S11.1080p.WEBRip.x265-RARBG/Greys.Anatomy.S11E18.1080p.WEBRip.x265-RARBG.mp4",
      "link": "torbox://4336321/13",
      "account_id": "",
      "generated": "0001-01-01T00:00:00Z",
      "deleted": false
    },
    "Greys.Anatomy.S11E19.1080p.WEBRip.x265-RARBG.mp4": {
      "torrent_id": "4336321",
      "id": "2",
      "name": "Greys.Anatomy.S11E19.1080p.WEBRip.x265-RARBG.mp4",
      "size": 719892428,
      "is_rar": false,
      "path": "Greys.Anatomy.S11.1080p.WEBRip.x265-RARBG/Greys.Anatomy.S11E19.1080p.WEBRip.x265-RARBG.mp4",
      "link": "torbox://4336321/2",
      "account_id": "",
      "generated": "0001-01-01T00:00:00Z",
      "deleted": false
    },
    "Greys.Anatomy.S11E20.1080p.WEBRip.x265-RARBG.mp4": {
      "torrent_id": "4336321",
      "id": "23",
      "name": "Greys.Anatomy.S11E20.1080p.WEBRip.x265-RARBG.mp4",
      "size": 720229622,
      "is_rar": false,
      "path": "Greys.Anatomy.S11.1080p.WEBRip.x265-RARBG/Greys.Anatomy.S11E20.1080p.WEBRip.x265-RARBG.mp4",
      "link": "torbox://4336321/23",
      "account_id": "",
      "generated": "0001-01-01T00:00:00Z",
      "deleted": false
    },
    "Greys.Anatomy.S11E21.1080p.WEBRip.x265-RARBG.mp4": {
      "torrent_id": "4336321",
      "id": "1",
      "name": "Greys.Anatomy.S11E21.1080p.WEBRip.x265-RARBG.mp4",
      "size": 719984196,
      "is_rar": false,
      "path": "Greys.Anatomy.S11.1080p.WEBRip.x265-RARBG/Greys.Anatomy.S11E21.1080p.WEBRip.x265-RARBG.mp4",
      "link": "torbox://4336321/1",
      "account_id": "",
      "generated": "0001-01-01T00:00:00Z",
      "deleted": false
    },
    "Greys.Anatomy.S11E22E23.1080p.WEBRip.x265-RARBG.mp4": {
      "torrent_id": "4336321",
      "id": "11",
      "name": "Greys.Anatomy.S11E22E23.1080p.WEBRip.x265-RARBG.mp4",
      "size": 1381539323,
      "is_rar": false,
      "path": "Greys.Anatomy.S11.1080p.WEBRip.x265-RARBG/Greys.Anatomy.S11E22E23.1080p.WEBRip.x265-RARBG.mp4",
      "link": "torbox://4336321/11",
      "account_id": "",
      "generated": "0001-01-01T00:00:00Z",
      "deleted": false
    },
    "Greys.Anatomy.S11E24.1080p.WEBRip.x265-RARBG.mp4": {
      "torrent_id": "4336321",
      "id": "24",
      "name": "Greys.Anatomy.S11E24.1080p.WEBRip.x265-RARBG.mp4",
      "size": 720123199,
      "is_rar": false,
      "path": "Greys.Anatomy.S11.1080p.WEBRip.x265-RARBG/Greys.Anatomy.S11E24.1080p.WEBRip.x265-RARBG.mp4",
      "link": "torbox://4336321/24",
      "account_id": "",
      "generated": "0001-01-01T00:00:00Z",
      "deleted": false
    },
    "Greys.Anatomy.S11E25.1080p.WEBRip.x265-RARBG.mp4": {
      "torrent_id": "4336321",
      "id": "0",
      "name": "Greys.Anatomy.S11E25.1080p.WEBRip.x265-RARBG.mp4",
      "size": 717503394,
      "is_rar": false,
      "path": "Greys.Anatomy.S11.1080p.WEBRip.x265-RARBG/Greys.Anatomy.S11E25.1080p.WEBRip.x265-RARBG.mp4",
      "link": "torbox://4336321/0",
      "account_id": "",
      "generated": "0001-01-01T00:00:00Z",
      "deleted": false
    }
  },
  "status": "downloaded",
  "added": "2025-09-24T18:23:35Z",
  "progress": 100,
  "speed": 0,
  "seeders": 0,
  "links": null,
  "mount_path": "/mounts/TorBox",
  "deleted_files": null,
  "debrid": "torbox",
  "arr": null,
  "added_on": "2025-09-24T18:23:35Z",
  "is_complete": true,
  "bad": false
}